{"blog-sidebar":{"search-2":{"title":"Search Here"},"categories-2":{"title":"Categories","count":0,"hierarchical":0,"dropdown":0},"tp-latest-posts-2":{"title":"Recent Post","count":"4","posts_order":"DESC"},"tag_cloud-2":{"title":"","count":0,"taxonomy":"post_tag"},"media_gallery-2":{"title":"Gallery","ids":[85,86,87,88,90,89],"columns":3,"size":"thumbnail","link_type":"post","orderby_random":false}},"footer-1":{"custom_html-2":{"title":"","content":"<div class=\"footer-widget__logo\">\r\n\t<a href=\"https:\/\/xqodex.xyz\/wpbelco\/belco\/\"><img src=\"https:\/\/xqodex.xyz\/wpbelco\/belco\/wp-content\/uploads\/2023\/12\/footer-logo.png\" alt=\"logo\" \/><\/a>\r\n<\/div>\r\n<p class=\"footer-widget__about-text\">\r\nLorem Ipsum is simply dummy text of printing and typesetting industry.\r\n<\/p>\r\n<div class=\"site-footer__social\">\r\n<a href=\"https:\/\/twitter.com\/\"><i class=\"fa-brands fa-x-twitter\"><\/i><\/a>\r\n<a href=\"https:\/\/www.facebook.com\/\"><i class=\"fa-brands fa-facebook-f\"><\/i><\/a>\r\n<a href=\"https:\/\/www.pinterest.com\/\"><i class=\"fab fa-pinterest-p\"><\/i><\/a>\r\n<a href=\"https:\/\/www.instagram.com\/\"><i class=\"fab fa-instagram\"><\/i><\/a>\r\n<\/div>\r\n"}},"footer-2":{"custom_html-8":{"title":"","content":"<div class=\"ml-company-one\">\r\n\t\r\n<div class=\"footer-widget__title-box\">\r\n<h3 class=\"footer-widget__title\">Company<\/h3>\r\n<\/div>\r\n<ul class=\"footer-widget__company-list list-unstyled\">\r\n<li><a href=\"https:\/\/xqodex.xyz\/wpbelco\/belco\/service-details\/\">Business planning<\/a><\/li>\r\n<li><a href=\"https:\/\/xqodex.xyz\/wpbelco\/belco\/service-details\/\">Tax strategy <\/a><\/li>\r\n<li><a href=\"https:\/\/xqodex.xyz\/wpbelco\/belco\/service-details\/\">Financial advices <\/a><\/li>\r\n<li><a href=\"https:\/\/xqodex.xyz\/wpbelco\/belco\/service-details\/\">Insurance strategy <\/a><\/li>\r\n<\/ul>\r\n<\/div>"}},"footer-3":{"custom_html-3":{"title":"","content":"<div class=\"news-border-1\"> \r\n<div class=\"footer-widget__column footer-widget__newsletter\">\r\n<div class=\"footer-widget__title-box\">\r\n<h3 class=\"footer-widget__title\">Newsletter<\/h3>\r\n<\/div>\r\n<p class=\"footer-widget__newsletter-text\">\r\nSign up for our latest news & articles. <br \/>\r\nWe won\u2019t give you spam mails.\r\n<\/p>\r\n<form class=\"footer-widget__newsletter-form mc-form\" data-url=\"MC_FORM_URL\" novalidate=\"novalidate\">\r\n<div class=\"footer-widget__newsletter-form-input-box\">\r\n<div class=\"input-border-2\"> \r\n<input type=\"email\" placeholder=\"Enter email address\" name=\"EMAIL\" \/>\r\n<\/div>\r\n<button type=\"submit\" class=\"footer-widget__newsletter-btn\">\r\n<span class=\"fas fa-paper-plane\"><\/span>\r\n<\/button>\r\n<\/div>\r\n<\/form>\r\n<div class=\"mc-form__response\"><\/div>\r\n<\/div>\r\n<\/div>"}},"footer-4":{"custom_html-4":{"title":"","content":"<div class=\"coninfo-1\">\r\n<div class=\"footer-widget__column footer-widget__contact\">\r\n<div class=\"footer-widget__title-box\">\r\n<h3 class=\"footer-widget__title\">You\u2019ve Questions<\/h3>\r\n<\/div>\r\n<ul class=\"footer-widget__contact-list list-unstyled\">\r\n<li>\r\n<div class=\"icon\">\r\n<span class=\"fa-sharp fa-light fa-location-dot\"><\/span>\r\n<\/div>\r\n<div class=\"content\">\r\n<h3>Location<\/h3>\r\n<p>915 Hill Street, USA<\/p>\r\n<\/div>\r\n<\/li>\r\n<li>\r\n<div class=\"icon\">\r\n<span class=\"fa-light fa-phone-volume\"><\/span>\r\n<\/div>\r\n<div class=\"content\">\r\n<h3>Get a quote<\/h3>\r\n<p><a href=\"tel:+13330000000\">+1(333) 000-0000<\/a><\/p>\r\n<\/div>\r\n<\/li>\r\n<li>\r\n<div class=\"icon\">\r\n<span class=\"fa-light fa-envelope\"><\/span>\r\n<\/div>\r\n<div class=\"content\">\r\n<h3>Send a mail<\/h3>\r\n<p><a href=\"mailto:example@email.com\">example@email.com<\/a><\/p>\r\n<\/div>\r\n<\/li>\r\n<\/ul>\r\n<\/div>\r\n<\/div>"}},"footer-2-1":{"custom_html-9":{"title":"","content":"<div class=\"footer-widget-two__logo\">\r\n\t<a href=\"https:\/\/xqodex.xyz\/wpbelco\/belco\/\"><img src=\"https:\/\/xqodex.xyz\/wpbelco\/belco\/wp-content\/uploads\/2023\/12\/logo-1.png\" alt=\"logo\" \/><\/a>\r\n<\/div>\r\n<p class=\"footer-widget-two__about-text\">\r\nWe work with a passion of taking<br \/>\r\nchallenges and creating new ones in<br \/>\r\nadvertising sector.\r\n<\/p>\r\n<div class=\"site-footer-two__social\">\r\n<a href=\"https:\/\/twitter.com\/\"><i class=\"fa-brands fa-x-twitter\"><\/i><\/a>\r\n<a href=\"https:\/\/www.facebook.com\/\"><i class=\"fa-brands fa-facebook-f\"><\/i><\/a>\r\n<a href=\"https:\/\/www.pinterest.com\/\"><i class=\"fab fa-pinterest-p\"><\/i><\/a>\r\n<a href=\"https:\/\/www.instagram.com\/\"><i class=\"fab fa-instagram\"><\/i><\/a>\r\n<\/div>\r\n"}},"footer-2-2":{"custom_html-10":{"title":"","content":"<div class=\"cmleft-margin\">\r\n\t\r\n<div class=\"footer-widget-two__title-box\">\r\n<h3 class=\"footer-widget-two__title\">Company<\/h3>\r\n<\/div>\r\n<ul class=\"footer-three footer-widget-two__company-list list-unstyled\">\r\n<li><a href=\"https:\/\/xqodex.xyz\/wpbelco\/belco\/service-details\/\">Business planning<\/a><\/li>\r\n<li><a href=\"https:\/\/xqodex.xyz\/wpbelco\/belco\/service-details\/\">Tax strategy <\/a><\/li>\r\n<li><a href=\"https:\/\/xqodex.xyz\/wpbelco\/belco\/service-details\/\">Financial advices <\/a><\/li>\r\n<li><a href=\"https:\/\/xqodex.xyz\/wpbelco\/belco\/service-details\/\">Insurance strategy <\/a><\/li>\r\n<\/ul>\r\n<\/div>"}},"footer-2-3":{"custom_html-11":{"title":"","content":"<div class=\"footer-widget-two__title-box\">\r\n<h3 class=\"footer-widget-two__title\">Instagram<\/h3>\r\n<\/div>\r\n<ul class=\"footer-widget-two__portfolio-list list-unstyled clearfix\">\r\n<li>\r\n<div class=\"footer-widget-two__portfolio-img\">\r\n<img src=\"https:\/\/xqodex.xyz\/wpbelco\/belco\/wp-content\/uploads\/2023\/11\/footer-widget-two-portfolio-img-1.jpg\" alt=\"logo\" \/>\r\n<a href=\"https:\/\/xqodex.xyz\/wpbelco\/belco\/\"><span class=\"fab fa-instagram\"><\/span><\/a>\r\n<\/div>\r\n<\/li>\r\n<li>\r\n<div class=\"footer-widget-two__portfolio-img\">\r\n<img src=\"https:\/\/xqodex.xyz\/wpbelco\/belco\/wp-content\/uploads\/2023\/11\/footer-widget-two-portfolio-img-2.jpg\" alt=\"logo\" \/>\r\n<a href=\"https:\/\/xqodex.xyz\/wpbelco\/belco\/\"><span class=\"fab fa-instagram\"><\/span><\/a>\r\n<\/div>\r\n<\/li>\r\n<li>\r\n<div class=\"footer-widget-two__portfolio-img\">\r\n<img src=\"https:\/\/xqodex.xyz\/wpbelco\/belco\/wp-content\/uploads\/2023\/11\/footer-widget-two-portfolio-img-3.jpg\" alt=\"logo\" \/>\r\n<a href=\"https:\/\/xqodex.xyz\/wpbelco\/belco\/\"><span class=\"fab fa-instagram\"><\/span><\/a>\r\n<\/div>\r\n<\/li>\r\n<li>\r\n<div class=\"footer-widget-two__portfolio-img\">\r\n<img src=\"https:\/\/xqodex.xyz\/wpbelco\/belco\/wp-content\/uploads\/2023\/11\/footer-widget-two-portfolio-img-4.jpg\" alt=\"logo\" \/>\r\n<a href=\"https:\/\/xqodex.xyz\/wpbelco\/belco\/\"><span class=\"fab fa-instagram\"><\/span><\/a>\r\n<\/div>\r\n<\/li>\r\n<li>\r\n<div class=\"footer-widget-two__portfolio-img\">\r\n<img src=\"https:\/\/xqodex.xyz\/wpbelco\/belco\/wp-content\/uploads\/2023\/11\/footer-widget-two-portfolio-img-6.jpg\" alt=\"\" \/>\r\n<a href=\"https:\/\/xqodex.xyz\/wpbelco\/belco\/\"><span class=\"fab fa-instagram\"><\/span><\/a>\r\n<\/div>\r\n<\/li>\r\n<li>\r\n<div class=\"footer-widget-two__portfolio-img\">\r\n<img src=\"https:\/\/xqodex.xyz\/wpbelco\/belco\/wp-content\/uploads\/2023\/11\/footer-widget-two-portfolio-img-5.jpg\" alt=\"\" \/>\r\n<a href=\"https:\/\/xqodex.xyz\/wpbelco\/belco\/\"><span class=\"fab fa-instagram\"><\/span><\/a>\r\n<\/div>\r\n<\/li>\r\n<\/ul>\r\n"}},"footer-2-4":{"custom_html-7":{"title":"","content":"<div class=\"ml-coninfo\">\r\n<div class=\"footer-widget-two__title-box\">\r\n<h3 class=\"footer-widget-two__title\">Contact info<\/h3>\r\n<\/div>\r\n<ul class=\"footer-widget-two__contact-list list-unstyled\">\r\n<li>\r\n<div class=\"icon\">\r\n<span class=\"fa-sharp fa-light fa-location-dot\"><\/span>\r\n<\/div>\r\n<p>915 Hill Street, USA<\/p>\r\n<\/li>\r\n<li>\r\n<div class=\"icon\">\r\n<span class=\"fa-light fa-phone-volume\"><\/span>\r\n<\/div>\r\n<p><a href=\"tel:+13330000000\">+1(333) 000-0000<\/a><\/p>\r\n<\/li>\r\n<li>\r\n<div class=\"icon\">\r\n<span class=\"fa-light fa-envelope\"><\/span>\r\n<\/div>\r\n<p><a href=\"mailto:example@email.com\">example@email.com<\/a><\/p>\r\n<\/li>\r\n<\/ul>\r\n<div class=\"footer-widget-two__work-time\">\r\n<div class=\"footer-widget-two__title-box\">\r\n<h3 class=\"footer-widget-two__title\">Working Time<\/h3>\r\n<\/div>\r\n<p class=\"footer-widget-two__work-time-text\">\r\nMon - Sat: 9:00 AM - 5:00 PM <br \/>\r\nSunday Close\r\n<\/p>\r\n<\/div>  \r\n<\/div>"}},"footer-3-1":{"custom_html-12":{"title":"","content":"<div class=\"footer-widget__logo\">\r\n\t<a href=\"https:\/\/xqodex.xyz\/wpbelco\/belco\/\"><img src=\"https:\/\/xqodex.xyz\/wpbelco\/belco\/wp-content\/uploads\/2023\/12\/logo-1.png\" alt=\"logo\" \/><\/a>\r\n<\/div>\r\n<p class=\"footer-widget__about-text\">\r\nLorem Ipsum is simply dummy text of <br \/>\r\nprinting and typesetting industry.\r\n<\/p>\r\n<div class=\"site-footer__social\">\r\n<a href=\"#\"><i class=\"fa-brands fa-x-twitter\"><\/i><\/a>\r\n<a href=\"#\"><i class=\"fa-brands fa-facebook-f\"><\/i><\/a>\r\n<a href=\"#\"><i class=\"fab fa-pinterest-p\"><\/i><\/a>\r\n<a href=\"#\"><i class=\"fab fa-instagram\"><\/i><\/a>\r\n<\/div>"}},"footer-3-2":{"custom_html-13":{"title":"","content":"<div class=\"news-border mr-company\"> \r\n<div class=\"footer-widget__title-box\">\r\n<h3 class=\"footer-widget__title\">Company<\/h3>\r\n<\/div>\r\n<ul class=\"footer-widget__company-list list-unstyled\">\r\n<li><a href=\"https:\/\/xqodex.xyz\/wpbelco\/belco\/service-details\/\">Business planning<\/a><\/li>\r\n<li><a href=\"https:\/\/xqodex.xyz\/wpbelco\/belco\/service-details\/\">Tax strategy <\/a><\/li>\r\n<li><a href=\"https:\/\/xqodex.xyz\/wpbelco\/belco\/service-details\/\">Financial advices <\/a><\/li>\r\n<li><a href=\"https:\/\/xqodex.xyz\/wpbelco\/belco\/service-details\/\">Insurance strategy <\/a><\/li>\r\n<\/ul>\r\n<\/div>"}},"footer-3-3":{"custom_html-14":{"title":"","content":"<div class=\"ml-news\">\r\n<div class=\"footer-widget__title-box\">\r\n<h3 class=\"footer-widget__title\">Newsletter<\/h3>\r\n<\/div>\r\n<p class=\"footer-widget__newsletter-text\">\r\nSign up for our latest news & articles. <br \/>\r\nWe won\u2019t give you spam mails.\r\n<\/p>\r\n<form class=\"footer-widget__newsletter-form mc-form\" data-url=\"MC_FORM_URL\" novalidate=\"novalidate\">\r\n<div class=\"footer-widget__newsletter-form-input-box\">\r\n<input type=\"email\" placeholder=\"Enter email address\" name=\"EMAIL\" \/>\r\n<button type=\"submit\" class=\"footer-widget__newsletter-btn\">\r\n<span class=\"fas fa-paper-plane\"><\/span>\r\n<\/button>\r\n<\/div>\r\n<\/form>\r\n<div class=\"mc-form__response\"><\/div>\r\n<\/div>"}},"footer-3-4":{"custom_html-15":{"title":"","content":"<div class=\"quistion-ml\">\r\n<div class=\"footer-widget__title-box\">\r\n<h3 class=\"footer-widget__title\">You\u2019ve Questions<\/h3>\r\n<\/div>\r\n<ul class=\"footer-widget__contact-list list-unstyled\">\r\n<li>\r\n<div class=\"icon\">\r\n<span class=\"fa-sharp fa-light fa-location-dot\"><\/span>\r\n<\/div>\r\n<div class=\"content\">\r\n<h3>Location<\/h3>\r\n<p>915 Hill Street, USA<\/p>\r\n<\/div>\r\n<\/li>\r\n<li>\r\n<div class=\"icon\">\r\n<span class=\"fa-light fa-phone-volume\"><\/span>\r\n<\/div>\r\n<div class=\"content\">\r\n<h3>Get a quote<\/h3>\r\n<p><a href=\"tel:+13330000000\">+1(333) 000-0000<\/a><\/p>\r\n<\/div>\r\n<\/li>\r\n<li>\r\n<div class=\"icon\">\r\n<span class=\"fa-light fa-envelope\"><\/span>\r\n<\/div>\r\n<div class=\"content\">\r\n<h3>Send a mail<\/h3>\r\n<p><a href=\"mailto:example@email.com\">example@email.com<\/a><\/p>\r\n<\/div>\r\n<\/li>\r\n<\/ul>\r\n<\/div>"}}}